django_verified_email_field-1.10.1.dist-info/licenses/LICENSE
verified_email_field/__init__.py
verified_email_field/apps.py
verified_email_field/auth.py
verified_email_field/fieldsetup.py
verified_email_field/forms.py
verified_email_field/models.py
verified_email_field/settings.py
verified_email_field/urls.py
verified_email_field/utils.py
verified_email_field/views.py
verified_email_field/widgets.py
verified_email_field/locale/cs/LC_MESSAGES/django.mo
verified_email_field/locale/cs/LC_MESSAGES/django.po
verified_email_field/migrations/__init__.py
verified_email_field/static/verified_email_field/send.js
verified_email_field/templates/verified_email_field/field.html
verified_email_field/templates/verified_email_field/mail.html
verified_email_field/templates/verified_email_field/mail.txt
django_verified_email_field-1.10.1.dist-info/METADATA
django_verified_email_field-1.10.1.dist-info/WHEEL
django_verified_email_field-1.10.1.dist-info/top_level.txt
django_verified_email_field-1.10.1.dist-info/RECORD
